cd_drive/__init__.py
cd_drive/drive.py
cd_drive-0.1.dist-info/LICENSE
cd_drive-0.1.dist-info/METADATA
cd_drive-0.1.dist-info/WHEEL
cd_drive-0.1.dist-info/top_level.txt
cd_drive-0.1.dist-info/RECORD
