Metadata-Version: 2.1
Name: cd-drive
Version: 0.1
Summary: Wrapper to easily manipulate Google Drive files
Home-page: https://github.com/matheusbsilva/cd_drive
License: MIT
Platform: UNKNOWN
Classifier: Programming Language :: Python :: 3
Classifier: License :: OSI Approved :: MIT License
Classifier: Operating System :: OS Independent
Requires-Python: >=3.6
Requires-Dist: google-api-python-client (==1.7.12)
Requires-Dist: google-auth-httplib2 (==0.0.3)
Requires-Dist: google-auth-oauthlib (==0.4.1)
